{
  "Rooms": [
    {
      "roomId": "5b213785c13d798f200a4e55",
      "location": "Reston",
      "vacancy": 2,
      "occupancy": 4,
      "gender": "female",
      "address": {
        "address1": "Livingston",
        "address2": 338,
        "city": "<ReferenceError: loc is not defined>",
        "state": "Virginia",
        "postalCode": 27711,
        "country": "USA"
      }
    },
    {
      "roomId": "5b21378522c5a21805a5d826",
      "location": "Reston",
      "vacancy": 4,
      "occupancy": 2,
      "gender": "male",
      "address": {
        "address1": "Fowler",
        "address2": 316,
        "city": "<ReferenceError: loc is not defined>",
        "state": "Virginia",
        "postalCode": 83296,
        "country": "USA"
      }
    },
    {
      "roomId": "5b213785d1ac9a80b3edc2d4",
      "location": "Tampa",
      "vacancy": 5,
      "occupancy": 1,
      "gender": "male",
      "address": {
        "address1": "Bearss",
        "address2": 266,
        "city": "<ReferenceError: loc is not defined>",
        "state": "Florida",
        "postalCode": 42351,
        "country": "USA"
      }
    },
    {
      "roomId": "5b213785b02e1f8ef0d1108f",
      "location": "Reston",
      "vacancy": 4,
      "occupancy": 2,
      "gender": "female",
      "address": {
        "address1": "Fowler",
        "address2": 336,
        "city": "<ReferenceError: loc is not defined>",
        "state": "Virginia",
        "postalCode": 83592,
        "country": "USA"
      }
    },
    {
      "roomId": "5b21378576c100a5aa311799",
      "location": "Tampa",
      "vacancy": 1,
      "occupancy": 5,
      "gender": "male",
      "address": {
        "address1": "Fowler",
        "address2": 364,
        "city": "<ReferenceError: loc is not defined>",
        "state": "Florida",
        "postalCode": 63794,
        "country": "USA"
      }
    },
    {
      "roomId": "5b21378516f12cc4b3456d36",
      "location": "Reston",
      "vacancy": 3,
      "occupancy": 3,
      "gender": "male",
      "address": {
        "address1": "Bearss",
        "address2": 330,
        "city": "<ReferenceError: loc is not defined>",
        "state": "Virginia",
        "postalCode": 37395,
        "country": "USA"
      }
    },
    {
      "roomId": "5b213785f74569f63c480b93",
      "location": "Reston",
      "vacancy": 4,
      "occupancy": 2,
      "gender": "male",
      "address": {
        "address1": "Fowler",
        "address2": 403,
        "city": "<ReferenceError: loc is not defined>",
        "state": "Florida",
        "postalCode": 55668,
        "country": "USA"
      }
    },
    {
      "roomId": "5b213785ecff38aa86c2f9c9",
      "location": "Tampa",
      "vacancy": 4,
      "occupancy": 2,
      "gender": "male",
      "address": {
        "address1": "Fowler",
        "address2": 559,
        "city": "<ReferenceError: loc is not defined>",
        "state": "Virginia",
        "postalCode": 68164,
        "country": "USA"
      }
    },
    {
      "roomId": "5b213785aad5f67cd0c5383f",
      "location": "Reston",
      "vacancy": 6,
      "occupancy": 0,
      "gender": "female",
      "address": {
        "address1": "Fowler",
        "address2": 414,
        "city": "<ReferenceError: loc is not defined>",
        "state": "Virginia",
        "postalCode": 56527,
        "country": "USA"
      }
    },
    {
      "roomId": "5b213785164a5a1ec928d1c5",
      "location": "Reston",
      "vacancy": 4,
      "occupancy": 2,
      "gender": "female",
      "address": {
        "address1": "Livingston",
        "address2": 367,
        "city": "<ReferenceError: loc is not defined>",
        "state": "Virginia",
        "postalCode": 56888,
        "country": "USA"
      }
    }
  ],
  "Users": 
  [
    {
      "id": "5b1ffa5b722aaf457bd4d4e4",
      "location": "Chicago",
      "email": "dyergrant@ultrimax.com",
      "gender": "male",
      "type": "Unknown",
      "batch": null,
      "room": null,
      "name": {
        "id": "5b1ffa5b140ffdfea5a0def1",
        "first": "Delia",
        "middle": "Mcfadden",
        "last": "Golden"
      },
      "address": {
        "address1": "Fowler",
        "address2": 595,
        "city": "Chicago",
        "state": "Virginia",
        "postalCode": 86081,
        "country": "USA"
      }
    },
    {
      "id": "5b1ffa5b8a1d6a3a16a865a5",
      "location": "Here",
      "email": "mcfaddengolden@ultrimax.com",
      "gender": "male",
      "type": "Known",
      "batch": null,
      "room": null,
      "name": {
        "id": "5b1ffa5b37021f58c705bdd9",
        "first": "Mcintyre",
        "middle": "Tabitha",
        "last": "Ashley"
      },
      "address": {
        "address1": "Fowler",
        "address2": 135,
        "city": "Here",
        "state": "Florida",
        "postalCode": 35897,
        "country": "USA"
      }
    },
    {
      "id": "5b1ffa5ba6d5140cf8ef59da",
      "location": "Reston",
      "email": "tabithaashley@ultrimax.com",
      "gender": "female",
      "type": "Unknown",
      "batch": null,
      "room": null,
      "name": {
        "id": "5b1ffa5bb0904dd66ef2fa23",
        "first": "Geraldine",
        "middle": "Sabrina",
        "last": "Palmer"
      },
      "address": {
        "address1": "Bearss",
        "address2": 295,
        "city": "Reston",
        "state": "Florida",
        "postalCode": 80522,
        "country": "USA"
      }
    },
    {
      "id": "5b1ffa5bf7f8adf9e05069f7",
      "location": "Miami",
      "email": "sabrinapalmer@ultrimax.com",
      "gender": "female",
      "type": "Known",
      "batch": null,
      "room": null,
      "name": {
        "id": "5b1ffa5bd9f9f7a893ad6f78",
        "first": "Claudia",
        "middle": "Brenda",
        "last": "Bowman"
      },
      "address": {
        "address1": "Livingston",
        "address2": 515,
        "city": "Miami",
        "state": "Virginia",
        "postalCode": 91818,
        "country": "USA"
      }
    },
    {
      "id": "5b1ffa5b5c8e1d32517ea7ef",
      "location": "Valley",
      "email": "brendabowman@ultrimax.com",
      "gender": "female",
      "type": "Unknown",
      "batch": null,
      "room": null,
      "name": {
        "id": "5b1ffa5b9b9d5ec2bca7c627",
        "first": "Bartlett",
        "middle": "House",
        "last": "Parsons"
      },
      "address": {
        "address1": "Livingston",
        "address2": 365,
        "city": "Valley",
        "state": "Florida",
        "postalCode": 51779,
        "country": "USA"
      }
    },
    {
      "id": "5b1ffa5bc4d5ac1d3e07d6eb",
      "location": "Miami",
      "email": "houseparsons@ultrimax.com",
      "gender": "male",
      "type": "Undefined",
      "batch": null,
      "room": null,
      "name": {
        "id": "5b1ffa5bec075a48e0f2c919",
        "first": "Avery",
        "middle": "Owens",
        "last": "Cash"
      },
      "address": {
        "address1": "Livingston",
        "address2": 180,
        "city": "Miami",
        "state": "Florida",
        "postalCode": 15538,
        "country": "USA"
      }
    },
    {
      "id": "5b1ffa5b722d696c4f168f1d",
      "location": "Tampa",
      "email": "owenscash@ultrimax.com",
      "gender": "male",
      "type": "Undefined",
      "batch": null,
      "room": null,
      "name": {
        "id": "5b1ffa5b8768edb95cbf2c66",
        "first": "Clay",
        "middle": "Christina",
        "last": "Reynolds"
      },
      "address": {
        "address1": "Bearss",
        "address2": 397,
        "city": "Tampa",
        "state": "Florida",
        "postalCode": 43709,
        "country": "USA"
      }
    },
    {
      "id": "5b1ffa5bc3ec48ba229b2984",
      "location": "New York",
      "email": "christinareynolds@ultrimax.com",
      "gender": "female",
      "type": "Known",
      "batch": null,
      "room": null,
      "name": {
        "id": "5b1ffa5bfda2ba80b9b95dcc",
        "first": "Dominique",
        "middle": "Kayla",
        "last": "Walsh"
      },
      "address": {
        "address1": "Livingston",
        "address2": 527,
        "city": "New York",
        "state": "Virginia",
        "postalCode": 24173,
        "country": "USA"
      }
    },
    {
      "id": "5b1ffa5bd71a831ba5cc51f7",
      "location": "New York",
      "email": "kaylawalsh@ultrimax.com",
      "gender": "female",
      "type": "Undefined",
      "batch": null,
      "room": null,
      "name": {
        "id": "5b1ffa5bd1ff77a85be87fcd",
        "first": "Donovan",
        "middle": "Travis",
        "last": "Russell"
      },
      "address": {
        "address1": "Bearss",
        "address2": 424,
        "city": "New York",
        "state": "Florida",
        "postalCode": 96307,
        "country": "USA"
      }
    },
    {
      "id": "5b1ffa5b79946eeb6cea2af5",
      "location": "Chicago",
      "email": "travisrussell@ultrimax.com",
      "gender": "male",
      "type": "Unknown",
      "batch": null,
      "room": null,
      "name": {
        "id": "5b1ffa5b8a97976150f03b11",
        "first": "Robert",
        "middle": "Ina",
        "last": "Leblanc"
      },
      "address": {
        "address1": "Bearss",
        "address2": 324,
        "city": "Chicago",
        "state": "Virginia",
        "postalCode": 99979,
        "country": "USA"
      }
    }
  ]
  }